DESCRIPTION.rst
MANIFEST.in
setup.py
pyvistaconnector/__init__.py
pyvistaconnector/pyvistaconnector.py
pyvistaconnector.egg-info/PKG-INFO
pyvistaconnector.egg-info/SOURCES.txt
pyvistaconnector.egg-info/dependency_links.txt
pyvistaconnector.egg-info/requires.txt
pyvistaconnector.egg-info/top_level.txt