Metadata-Version: 1.0
Name: pyvistaconnector
Version: 0.1.3
Summary: AlterVistaThesaurus connector
Home-page: https://github.com/tttthomasssss/nlp-utils/tree/master/ThesaurusConnectors/AlterVistaConnector
Author: tttthomasssss
Author-email: tttthomasssss@gmail.com
License: MIT
Keywords: nlp altervistathesaurus thesaurus
Platform: UNKNOWN
Classifier: Development Status :: 4 - Beta
Classifier: Intended Audience :: Developers
Classifier: Intended Audience :: Science/Research
Classifier: Topic :: Scientific/Engineering :: Artificial Intelligence
Classifier: Topic :: Software Development :: Libraries :: Python Modules
Classifier: License :: OSI Approved :: MIT License
Classifier: Programming Language :: Python :: 2.7
Classifier: Programming Language :: Python :: 3
Classifier: Programming Language :: Python :: 3.2
Classifier: Programming Language :: Python :: 3.3
Classifier: Programming Language :: Python :: 3.4
